elluminate/__init__.py
elluminate/client.py
elluminate/utils.py
elluminate/resources/__init__.py
elluminate/resources/base.py
elluminate/resources/criteria.py
elluminate/resources/criterion_sets.py
elluminate/resources/experiments.py
elluminate/resources/llm_configs.py
elluminate/resources/projects.py
elluminate/resources/prompt_templates.py
elluminate/resources/ratings.py
elluminate/resources/responses.py
elluminate/resources/template_variables.py
elluminate/resources/template_variables_collections.py
elluminate/schemas/__init__.py
elluminate/schemas/base.py
elluminate/schemas/conversation.py
elluminate/schemas/criterion.py
elluminate/schemas/criterion_set.py
elluminate/schemas/experiments.py
elluminate/schemas/generation_metadata.py
elluminate/schemas/generation_params.py
elluminate/schemas/llm_config.py
elluminate/schemas/organization.py
elluminate/schemas/project.py
elluminate/schemas/prompt.py
elluminate/schemas/prompt_template.py
elluminate/schemas/rating.py
elluminate/schemas/response.py
elluminate/schemas/template_variables.py
elluminate/schemas/template_variables_collection.py
elluminate-0.7.3.dist-info/METADATA
elluminate-0.7.3.dist-info/WHEEL
elluminate-0.7.3.dist-info/RECORD
