Metadata-Version: 2.4
Name: elluminate
Version: 0.7.3
Summary: The Official Elluminate SDK
Project-URL: Documentation, https://docs.elluminate.de
Author: ellamind GmbH
Requires-Python: <3.14,>=3.10
Requires-Dist: httpx-sse==0.4.1
Requires-Dist: loguru>=0.7.3
Requires-Dist: openai>=1.63.2
Requires-Dist: pydantic>=2.10.6
Requires-Dist: requests>=2.32.3
Requires-Dist: tenacity>=9.0.0
Requires-Dist: tqdm>=4.67.1
Provides-Extra: examples
Requires-Dist: beautifulsoup4>=4.13.3; extra == 'examples'
Requires-Dist: langchain-community>=0.3.18; extra == 'examples'
Requires-Dist: langchain-core>=0.3.37; extra == 'examples'
Requires-Dist: langchain-openai>=0.3.6; extra == 'examples'
Requires-Dist: langchain-text-splitters>=0.3.6; extra == 'examples'
Requires-Dist: pyfakefs>=5.8.0; extra == 'examples'
Requires-Dist: python-dotenv>=1.0.1; extra == 'examples'
